LICENSE
README.md
setup.py
git_me_the_url.egg-info/PKG-INFO
git_me_the_url.egg-info/SOURCES.txt
git_me_the_url.egg-info/dependency_links.txt
git_me_the_url.egg-info/entry_points.txt
git_me_the_url.egg-info/requires.txt
git_me_the_url.egg-info/top_level.txt
gitmetheurl/__about__.py
gitmetheurl/__init__.py
gitmetheurl/__main__.py
gitmetheurl/base.py
gitmetheurl/cmd.py
gitmetheurl/entry_points.py
gitmetheurl/plugin_loader.py
gitmetheurl/translators/__init__.py
gitmetheurl/translators/bitbucket.py
gitmetheurl/translators/github.py
gitmetheurl/translators/gitlab.py
gitmetheurl/translators/translator.py