Metadata-Version: 2.1
Name: git-me-the-url
Version: 2.1.0
Summary: Generate sharable links to your Git source
Home-page: https://github.com/amykyta3/git-me-the-url
Author: Alex Mykyta
Author-email: amykyta3@github.com
License: UNKNOWN
Project-URL: Source, https://github.com/amykyta3/git-me-the-url
Project-URL: Tracker, https://github.com/amykyta3/git-me-the-url/issues
Platform: UNKNOWN
Classifier: Development Status :: 5 - Production/Stable
Classifier: Programming Language :: Python
Classifier: Programming Language :: Python :: 3
Classifier: Programming Language :: Python :: 3.5
Classifier: Programming Language :: Python :: 3.6
Classifier: Programming Language :: Python :: 3.7
Classifier: Programming Language :: Python :: 3.8
Classifier: Programming Language :: Python :: 3.9
Classifier: Programming Language :: Python :: 3 :: Only
Classifier: Intended Audience :: Developers
Classifier: License :: OSI Approved :: GNU General Public License v3 (GPLv3)
Classifier: Operating System :: OS Independent
Classifier: Topic :: Software Development :: Version Control :: Git
